airflow/providers/elasticsearch/__init__.py
airflow/providers/elasticsearch/common/__init__.py
airflow/providers/elasticsearch/common/utils/__init__.py
airflow/providers/elasticsearch/common/utils/log/__init__.py
airflow/providers/elasticsearch/common/utils/log/file_task_handler.py
airflow/providers/elasticsearch/hooks/__init__.py
airflow/providers/elasticsearch/hooks/elasticsearch.py
airflow/providers/elasticsearch/log/__init__.py
airflow/providers/elasticsearch/log/es_task_handler.py
apache_airflow_backport_providers_elasticsearch-2021.3.17.dist-info/LICENSE
apache_airflow_backport_providers_elasticsearch-2021.3.17.dist-info/METADATA
apache_airflow_backport_providers_elasticsearch-2021.3.17.dist-info/NOTICE
apache_airflow_backport_providers_elasticsearch-2021.3.17.dist-info/WHEEL
apache_airflow_backport_providers_elasticsearch-2021.3.17.dist-info/top_level.txt
apache_airflow_backport_providers_elasticsearch-2021.3.17.dist-info/RECORD
